{"nodes":[{"id":"smarco_screenshot_04","label":"Smarco E-Commerce App - Product Listing","file_type":"image","source_file":".reference/screenshots/smarco_screenshot_04.jpg","source_location":null,"source_url":null,"captured_at":null,"author":null,"contributor":null},{"id":"smarco_screenshot_05","label":"Smarco E-Commerce App - Product Detail Page","file_type":"image","source_file":".reference/screenshots/smarco_screenshot_05.jpg","source_location":null,"source_url":null,"captured_at":null,"author":null,"contributor":null},{"id":"smarco_screenshot_06","label":"Smarco E-Commerce App - User Profile","file_type":"image","source_file":".reference/screenshots/smarco_screenshot_06.jpg","source_location":null,"source_url":null,"captured_at":null,"author":null,"contributor":null},{"id":"akuberbagi_website","label":"Aku Berbagi Charity Website","file_type":"image","source_file":".reference/websites/akuberbagi_website.jpg","source_location":null,"source_url":null,"captured_at":null,"author":null,"contributor":null},{"id":"bhayangkari_youtube","label":"Bhayangkari YouTube Channel Screenshot","file_type":"image","source_file":".reference/websites/bhayangkari_youtube.jpg","source_location":null,"source_url":null,"captured_at":null,"author":null,"contributor":null},{"id":"gogreat_website","label":"Great Eastern GoGreat Insurance Website","file_type":"image","source_file":".reference/websites/gogreat_website.jpg","source_location":null,"source_url":null,"captured_at":null,"author":null,"contributor":null},{"id":"kuismilioner_website","label":"Kuis Milioner Game Voucher Website","file_type":"image","source_file":".reference/websites/kuismilioner_website.jpg","source_location":null,"source_url":null,"captured_at":null,"author":null,"contributor":null},{"id":"labamu_website","label":"Labamu Business Growth Platform Website","file_type":"image","source_file":".reference/websites/labamu_website.jpg","source_location":null,"source_url":null,"captured_at":null,"author":null,"contributor":null},{"id":"mybeepr_website","label":"myBeepr Clinical Communication App Listing","file_type":"image","source_file":".reference/websites/mybeepr_website.jpg","source_location":null,"source_url":null,"captured_at":null,"author":null,"contributor":null},{"id":"pancaagri_forest_bg","label":"Panca Agri Forest Background Image","file_type":"image","source_file":".reference/websites/pancaagri_forest_bg.jpg","source_location":null,"source_url":null,"captured_at":null,"author":null,"contributor":null},{"id":"pancaagri_hero_plantation","label":"Panca Agri Palm Oil Plantation Hero Image","file_type":"image","source_file":".reference/websites/pancaagri_hero_plantation.jpg","source_location":null,"source_url":null,"captured_at":null,"author":null,"contributor":null},{"id":"pancaagri_palmoil_aerial","label":"Panca Agri Palm Oil Aerial Photography","file_type":"image","source_file":".reference/websites/pancaagri_palmoil_aerial.jpg","source_location":null,"source_url":null,"captured_at":null,"author":null,"contributor":null},{"id":"pancaagri_website","label":"PT Panca Agro Niaga Lestari Website","file_type":"image","source_file":".reference/websites/pancaagri_website.jpg","source_location":null,"source_url":null,"captured_at":null,"author":null,"contributor":null},{"id":"telkominfra_hero_ship","label":"Telkom Infra Marine Cable Ship Hero Image","file_type":"image","source_file":".reference/websites/telkominfra_hero_ship.jpg","source_location":null,"source_url":null,"captured_at":null,"author":null,"contributor":null},{"id":"telkominfra_website","label":"Telkom Infra Corporate Website","file_type":"image","source_file":".reference/websites/telkominfra_website.jpg","source_location":null,"source_url":null,"captured_at":null,"author":null,"contributor":null},{"id":"smarco_app","label":"Smarco E-Commerce Mobile Application","file_type":"image","source_file":null,"source_location":null,"source_url":null,"captured_at":null,"author":null,"contributor":null},{"id":"pancaagri_company","label":"PT Panca Agro Niaga Lestari - Agricultural Company","file_type":"image","source_file":null,"source_location":null,"source_url":null,"captured_at":null,"author":null,"contributor":null},{"id":"telkominfra_company","label":"Telkom Infra - Telecommunications Infrastructure","file_type":"image","source_file":null,"source_location":null,"source_url":null,"captured_at":null,"author":null,"contributor":null},{"id":"ecommerce_ui_pattern","label":"E-Commerce Mobile UI Pattern","file_type":"image","source_file":null,"source_location":null,"source_url":null,"captured_at":null,"author":null,"contributor":null},{"id":"insurance_website_pattern","label":"Insurance Product Website Pattern","file_type":"image","source_file":null,"source_location":null,"source_url":null,"captured_at":null,"author":null,"contributor":null},{"id":"charity_website_pattern","label":"Charity Donation Website Pattern","file_type":"image","source_file":null,"source_location":null,"source_url":null,"captured_at":null,"author":null,"contributor":null},{"id":"agricultural_website_pattern","label":"Agricultural Corporate Website Pattern","file_type":"image","source_file":null,"source_location":null,"source_url":null,"captured_at":null,"author":null,"contributor":null},{"id":"corporate_website_pattern","label":"Corporate Infrastructure Website Pattern","file_type":"image","source_file":null,"source_location":null,"source_url":null,"captured_at":null,"author":null,"contributor":null},{"id":"flash_sale_feature","label":"Flash Sale E-Commerce Feature","file_type":"image","source_file":null,"source_location":null,"source_url":null,"captured_at":null,"author":null,"contributor":null},{"id":"product_detail_feature","label":"Product Detail Page Feature","file_type":"image","source_file":null,"source_location":null,"source_url":null,"captured_at":null,"author":null,"contributor":null},{"id":"user_profile_feature","label":"User Profile Dashboard Feature","file_type":"image","source_file":null,"source_location":null,"source_url":null,"captured_at":null,"author":null,"contributor":null},{"id":"referral_system_feature","label":"Referral Code System Feature","file_type":"image","source_file":null,"source_location":null,"source_url":null,"captured_at":null,"author":null,"contributor":null},{"id":"green_color_theme","label":"Green Color Theme Design","file_type":"image","source_file":null,"source_location":null,"source_url":null,"captured_at":null,"author":null,"contributor":null},{"id":"red_color_theme","label":"Red Color Theme Design","file_type":"image","source_file":null,"source_location":null,"source_url":null,"captured_at":null,"author":null,"contributor":null},{"id":"blue_color_theme","label":"Blue Color Theme Design","file_type":"image","source_file":null,"source_location":null,"source_url":null,"captured_at":null,"author":null,"contributor":null},{"id":"indonesian_market","label":"Indonesian Digital Market","file_type":"image","source_file":null,"source_location":null,"source_url":null,"captured_at":null,"author":null,"contributor":null}],"edges":[{"source":"smarco_screenshot_04","target":"smarco_app","relation":"participate_in","confidence":"EXTRACTED","confidence_score":1.0,"source_file":".reference/screenshots/smarco_screenshot_04.jpg","source_location":null,"weight":1.0},{"source":"smarco_screenshot_05","target":"smarco_app","relation":"participate_in","confidence":"EXTRACTED","confidence_score":1.0,"source_file":".reference/screenshots/smarco_screenshot_05.jpg","source_location":null,"weight":1.0},{"source":"smarco_screenshot_06","target":"smarco_app","relation":"participate_in","confidence":"EXTRACTED","confidence_score":1.0,"source_file":".reference/screenshots/smarco_screenshot_06.jpg","source_location":null,"weight":1.0},{"source":"smarco_screenshot_04","target":"flash_sale_feature","relation":"conceptually_related_to","confidence":"EXTRACTED","confidence_score":1.0,"source_file":".reference/screenshots/smarco_screenshot_04.jpg","source_location":null,"weight":1.0},{"source":"smarco_screenshot_05","target":"product_detail_feature","relation":"conceptually_related_to","confidence":"EXTRACTED","confidence_score":1.0,"source_file":".reference/screenshots/smarco_screenshot_05.jpg","source_location":null,"weight":1.0},{"source":"smarco_screenshot_06","target":"user_profile_feature","relation":"conceptually_related_to","confidence":"EXTRACTED","confidence_score":1.0,"source_file":".reference/screenshots/smarco_screenshot_06.jpg","source_location":null,"weight":1.0},{"source":"smarco_screenshot_06","target":"referral_system_feature","relation":"conceptually_related_to","confidence":"EXTRACTED","confidence_score":1.0,"source_file":".reference/screenshots/smarco_screenshot_06.jpg","source_location":null,"weight":1.0},{"source":"smarco_screenshot_04","target":"green_color_theme","relation":"conceptually_related_to","confidence":"INFERRED","confidence_score":0.8,"source_file":".reference/screenshots/smarco_screenshot_04.jpg","source_location":null,"weight":1.0},{"source":"smarco_screenshot_05","target":"green_color_theme","relation":"conceptually_related_to","confidence":"INFERRED","confidence_score":0.8,"source_file":".reference/screenshots/smarco_screenshot_05.jpg","source_location":null,"weight":1.0},{"source":"smarco_screenshot_06","target":"green_color_theme","relation":"conceptually_related_to","confidence":"INFERRED","confidence_score":0.8,"source_file":".reference/screenshots/smarco_screenshot_06.jpg","source_location":null,"weight":1.0},{"source":"smarco_screenshot_04","target":"ecommerce_ui_pattern","relation":"conceptually_related_to","confidence":"EXTRACTED","confidence_score":1.0,"source_file":".reference/screenshots/smarco_screenshot_04.jpg","source_location":null,"weight":1.0},{"source":"smarco_screenshot_05","target":"ecommerce_ui_pattern","relation":"conceptually_related_to","confidence":"EXTRACTED","confidence_score":1.0,"source_file":".reference/screenshots/smarco_screenshot_05.jpg","source_location":null,"weight":1.0},{"source":"smarco_screenshot_06","target":"ecommerce_ui_pattern","relation":"conceptually_related_to","confidence":"EXTRACTED","confidence_score":1.0,"source_file":".reference/screenshots/smarco_screenshot_06.jpg","source_location":null,"weight":1.0},{"source":"akuberbagi_website","target":"charity_website_pattern","relation":"conceptually_related_to","confidence":"EXTRACTED","confidence_score":1.0,"source_file":".reference/websites/akuberbagi_website.jpg","source_location":null,"weight":1.0},{"source":"akuberbagi_website","target":"green_color_theme","relation":"conceptually_related_to","confidence":"INFERRED","confidence_score":0.8,"source_file":".reference/websites/akuberbagi_website.jpg","source_location":null,"weight":1.0},{"source":"gogreat_website","target":"insurance_website_pattern","relation":"conceptually_related_to","confidence":"EXTRACTED","confidence_score":1.0,"source_file":".reference/websites/gogreat_website.jpg","source_location":null,"weight":1.0},{"source":"gogreat_website","target":"red_color_theme","relation":"conceptually_related_to","confidence":"INFERRED","confidence_score":0.8,"source_file":".reference/websites/gogreat_website.jpg","source_location":null,"weight":1.0},{"source":"labamu_website","target":"blue_color_theme","relation":"conceptually_related_to","confidence":"INFERRED","confidence_score":0.8,"source_file":".reference/websites/labamu_website.jpg","source_location":null,"weight":1.0},{"source":"pancaagri_website","target":"pancaagri_company","relation":"participate_in","confidence":"EXTRACTED","confidence_score":1.0,"source_file":".reference/websites/pancaagri_website.jpg","source_location":null,"weight":1.0},{"source":"pancaagri_forest_bg","target":"pancaagri_company","relation":"participate_in","confidence":"INFERRED","confidence_score":0.7,"source_file":".reference/websites/pancaagri_forest_bg.jpg","source_location":null,"weight":1.0},{"source":"pancaagri_hero_plantation","target":"pancaagri_company","relation":"participate_in","confidence":"INFERRED","confidence_score":0.7,"source_file":".reference/websites/pancaagri_hero_plantation.jpg","source_location":null,"weight":1.0},{"source":"pancaagri_palmoil_aerial","target":"pancaagri_company","relation":"participate_in","confidence":"INFERRED","confidence_score":0.7,"source_file":".reference/websites/pancaagri_palmoil_aerial.jpg","source_location":null,"weight":1.0},{"source":"pancaagri_website","target":"agricultural_website_pattern","relation":"conceptually_related_to","confidence":"EXTRACTED","confidence_score":1.0,"source_file":".reference/websites/pancaagri_website.jpg","source_location":null,"weight":1.0},{"source":"pancaagri_website","target":"green_color_theme","relation":"conceptually_related_to","confidence":"INFERRED","confidence_score":0.8,"source_file":".reference/websites/pancaagri_website.jpg","source_location":null,"weight":1.0},{"source":"telkominfra_website","target":"telkominfra_company","relation":"participate_in","confidence":"EXTRACTED","confidence_score":1.0,"source_file":".reference/websites/telkominfra_website.jpg","source_location":null,"weight":1.0},{"source":"telkominfra_hero_ship","target":"telkominfra_company","relation":"participate_in","confidence":"INFERRED","confidence_score":0.7,"source_file":".reference/websites/telkominfra_hero_ship.jpg","source_location":null,"weight":1.0},{"source":"telkominfra_website","target":"corporate_website_pattern","relation":"conceptually_related_to","confidence":"EXTRACTED","confidence_score":1.0,"source_file":".reference/websites/telkominfra_website.jpg","source_location":null,"weight":1.0},{"source":"telkominfra_website","target":"red_color_theme","relation":"conceptually_related_to","confidence":"INFERRED","confidence_score":0.8,"source_file":".reference/websites/telkominfra_website.jpg","source_location":null,"weight":1.0},{"source":"kuismilioner_website","target":"ecommerce_ui_pattern","relation":"conceptually_related_to","confidence":"INFERRED","confidence_score":0.7,"source_file":".reference/websites/kuismilioner_website.jpg","source_location":null,"weight":1.0},{"source":"mybeepr_website","target":"ecommerce_ui_pattern","relation":"conceptually_related_to","confidence":"INFERRED","confidence_score":0.6,"source_file":".reference/websites/mybeepr_website.jpg","source_location":null,"weight":1.0},{"source":"smarco_app","target":"indonesian_market","relation":"conceptually_related_to","confidence":"INFERRED","confidence_score":0.7,"source_file":".reference/screenshots/smarco_screenshot_04.jpg","source_location":null,"weight":1.0},{"source":"akuberbagi_website","target":"indonesian_market","relation":"conceptually_related_to","confidence":"INFERRED","confidence_score":0.7,"source_file":".reference/websites/akuberbagi_website.jpg","source_location":null,"weight":1.0},{"source":"gogreat_website","target":"indonesian_market","relation":"conceptually_related_to","confidence":"INFERRED","confidence_score":0.7,"source_file":".reference/websites/gogreat_website.jpg","source_location":null,"weight":1.0},{"source":"labamu_website","target":"indonesian_market","relation":"conceptually_related_to","confidence":"INFERRED","confidence_score":0.7,"source_file":".reference/websites/labamu_website.jpg","source_location":null,"weight":1.0},{"source":"pancaagri_company","target":"indonesian_market","relation":"conceptually_related_to","confidence":"INFERRED","confidence_score":0.7,"source_file":".reference/websites/pancaagri_website.jpg","source_location":null,"weight":1.0},{"source":"telkominfra_company","target":"indonesian_market","relation":"conceptually_related_to","confidence":"INFERRED","confidence_score":0.7,"source_file":".reference/websites/telkominfra_website.jpg","source_location":null,"weight":1.0},{"source":"smarco_screenshot_04","target":"smarco_screenshot_05","relation":"semantically_similar_to","confidence":"INFERRED","confidence_score":0.9,"source_file":".reference/screenshots/smarco_screenshot_04.jpg","source_location":null,"weight":1.0},{"source":"smarco_screenshot_05","target":"smarco_screenshot_06","relation":"semantically_similar_to","confidence":"INFERRED","confidence_score":0.9,"source_file":".reference/screenshots/smarco_screenshot_05.jpg","source_location":null,"weight":1.0},{"source":"pancaagri_forest_bg","target":"pancaagri_hero_plantation","relation":"semantically_similar_to","confidence":"INFERRED","confidence_score":0.9,"source_file":".reference/websites/pancaagri_forest_bg.jpg","source_location":null,"weight":1.0},{"source":"pancaagri_hero_plantation","target":"pancaagri_palmoil_aerial","relation":"semantically_similar_to","confidence":"INFERRED","confidence_score":0.9,"source_file":".reference/websites/pancaagri_hero_plantation.jpg","source_location":null,"weight":1.0},{"source":"pancaagri_forest_bg","target":"pancaagri_palmoil_aerial","relation":"semantically_similar_to","confidence":"INFERRED","confidence_score":0.8,"source_file":".reference/websites/pancaagri_forest_bg.jpg","source_location":null,"weight":1.0}],"hyperedges":[{"id":"smarco_app_screens","label":"Smarco App Screen Collection","nodes":["smarco_screenshot_04","smarco_screenshot_05","smarco_screenshot_06"],"relation":"participate_in","confidence":"EXTRACTED","confidence_score":1.0,"source_file":".reference/screenshots/smarco_screenshot_04.jpg"},{"id":"pancaagri_visual_assets","label":"Panca Agri Visual Asset Collection","nodes":["pancaagri_forest_bg","pancaagri_hero_plantation","pancaagri_palmoil_aerial","pancaagri_website"],"relation":"participate_in","confidence":"EXTRACTED","confidence_score":1.0,"source_file":".reference/websites/pancaagri_website.jpg"},{"id":"telkominfra_visual_assets","label":"Telkom Infra Visual Asset Collection","nodes":["telkominfra_hero_ship","telkominfra_website"],"relation":"participate_in","confidence":"EXTRACTED","confidence_score":1.0,"source_file":".reference/websites/telkominfra_website.jpg"},{"id":"green_theme_projects","label":"Green Themed Design Projects","nodes":["smarco_screenshot_04","smarco_screenshot_05","smarco_screenshot_06","akuberbagi_website","pancaagri_website"],"relation":"form","confidence":"INFERRED","confidence_score":0.75,"source_file":".reference/screenshots/smarco_screenshot_04.jpg"},{"id":"red_theme_projects","label":"Red Themed Design Projects","nodes":["gogreat_website","telkominfra_website"],"relation":"form","confidence":"INFERRED","confidence_score":0.75,"source_file":".reference/websites/gogreat_website.jpg"},{"id":"indonesian_portfolio_projects","label":"Indonesian Market Portfolio Projects","nodes":["smarco_app","akuberbagi_website","gogreat_website","labamu_website","pancaagri_company","telkominfra_company","kuismilioner_website"],"relation":"form","confidence":"INFERRED","confidence_score":0.7,"source_file":".reference/screenshots/smarco_screenshot_04.jpg"}],"input_tokens":0,"output_tokens":0}