{"nodes": [{"id": "e_work_ugansaripudin_porto_ugan_saripudin_porto_src_sections_experiencesection_tsx", "label": "ExperienceSection.tsx", "file_type": "code", "source_file": "E:\\work\\Ugansaripudin-porto\\ugan-saripudin-porto\\src\\sections\\ExperienceSection.tsx", "source_location": "L1"}], "edges": [{"source": "e_work_ugansaripudin_porto_ugan_saripudin_porto_src_sections_experiencesection_tsx", "target": "fadein", "relation": "imports_from", "confidence": "EXTRACTED", "source_file": "E:\\work\\Ugansaripudin-porto\\ugan-saripudin-porto\\src\\sections\\ExperienceSection.tsx", "source_location": "L1", "weight": 1.0}, {"source": "e_work_ugansaripudin_porto_ugan_saripudin_porto_src_sections_experiencesection_tsx", "target": "sectionheader", "relation": "imports_from", "confidence": "EXTRACTED", "source_file": "E:\\work\\Ugansaripudin-porto\\ugan-saripudin-porto\\src\\sections\\ExperienceSection.tsx", "source_location": "L2", "weight": 1.0}, {"source": "e_work_ugansaripudin_porto_ugan_saripudin_porto_src_sections_experiencesection_tsx", "target": "lucide_react", "relation": "imports_from", "confidence": "EXTRACTED", "source_file": "E:\\work\\Ugansaripudin-porto\\ugan-saripudin-porto\\src\\sections\\ExperienceSection.tsx", "source_location": "L3", "weight": 1.0}], "raw_calls": []}